birdsong/__init__.py
birdsong/rest.py
birdsong/sender.py
birdsong/tokens.py
birdsong/values.py
birdsong/view.py
birdsong-1.4.0.dist-info/licenses/LICENSE
birdsong-1.4.0.dist-info/METADATA
birdsong-1.4.0.dist-info/WHEEL
birdsong-1.4.0.dist-info/top_level.txt
birdsong-1.4.0.dist-info/RECORD
