Metadata-Version: 2.4
Name: birdsong
Version: 1.4.0
Summary: A Python API to Canary Lab's historian web services.
Author-email: Andrew Geiger <andrew@corsosystems.com>, Nick Fornicola <nfornicola@beusaenergy.com>
Maintainer-email: Nick Fornicola <nfornicola@beusaenergy.com>, Andrew Geiger <andrew@corsosystems.com>
License-Expression: Apache-2.0
Project-URL: Homepage, https://github.com/CorsoSource/birdsong
Project-URL: Documentation, https://github.com/CorsoSource/birdsong/blob/master/README.md
Project-URL: Repository, https://github.com/CorsoSource/birdsong.git
Project-URL: Bug Tracker, https://github.com/CorsoSource/birdsong/issues
Keywords: canary,historian,birdsong
Classifier: Development Status :: 4 - Beta
Classifier: Programming Language :: Python :: 3
Classifier: Operating System :: OS Independent
Requires-Python: >=3.9
License-File: LICENSE
Dynamic: license-file
